mylutils-0.3.0.dist-info/METADATA
mylutils-0.3.0.dist-info/WHEEL
mylutils-0.3.0.dist-info/licenses/LICENSE
mylutils/__init__.py
mylutils/mylutils.cpython-312-x86_64-linux-gnu.so
mylutils-0.3.0.dist-info/RECORD
